datatypes/__init__.py
datatypes/command.py
datatypes/compat.py
datatypes/copy.py
datatypes/csv.py
datatypes/datetime.py
datatypes/email.py
datatypes/enum.py
datatypes/event.py
datatypes/exception.py
datatypes/http.py
datatypes/logging.py
datatypes/number.py
datatypes/parse.py
datatypes/path.py
datatypes/profile.py
datatypes/server.py
datatypes/service.py
datatypes/ssh.py
datatypes/string.py
datatypes/typing.py
datatypes/url.py
datatypes/utils.py
datatypes/collections/__init__.py
datatypes/collections/container.py
datatypes/collections/mapping.py
datatypes/collections/sequence.py
datatypes/config/__init__.py
datatypes/config/parser.py
datatypes/config/settings.py
datatypes/config/environ/__init__.py
datatypes/config/environ/base.py
datatypes/config/environ/token.py
datatypes/decorators/__init__.py
datatypes/decorators/base.py
datatypes/decorators/descriptor.py
datatypes/decorators/misc.py
datatypes/filetypes/__init__.py
datatypes/filetypes/html.py
datatypes/filetypes/toml.py
datatypes/reflection/__init__.py
datatypes/reflection/inspect.py
datatypes/reflection/other.py
datatypes/reflection/path.py
datatypes/token/__init__.py
datatypes/token/abnf.py
datatypes/token/base.py
datatypes/token/word.py
datatypes-0.31.0.dist-info/licenses/LICENSE.txt
datatypes-0.31.0.dist-info/METADATA
datatypes-0.31.0.dist-info/WHEEL
datatypes-0.31.0.dist-info/top_level.txt
datatypes-0.31.0.dist-info/RECORD
