Metadata-Version: 2.4
Name: datatypes
Version: 0.31.0
Summary: Utility Classes and Functions that are handy across multiple projects
Author-email: Jay Marcyes <jay@marcyes.com>
License-Expression: MIT
Project-URL: Homepage, https://github.com/Jaymon/datatypes
Project-URL: Repository, https://github.com/Jaymon/datatypes
Classifier: Development Status :: 5 - Production/Stable
Classifier: Intended Audience :: Developers
Classifier: Operating System :: OS Independent
Classifier: Programming Language :: Python :: 3
Requires-Python: >=3.10
License-File: LICENSE.txt
Provides-Extra: tests
Requires-Dist: testdata; extra == "tests"
Provides-Extra: ssh
Requires-Dist: asyncssh; extra == "ssh"
Dynamic: license-file
